nrlvmd.py
setup.cfg
setup.py
nr_lvm_plugin.egg-info/PKG-INFO
nr_lvm_plugin.egg-info/SOURCES.txt
nr_lvm_plugin.egg-info/dependency_links.txt
nr_lvm_plugin.egg-info/requires.txt
nr_lvm_plugin.egg-info/top_level.txt