Metadata-Version: 1.1
Name: nr-lvm-plugin
Version: 0.1.4
Summary: Plugin to monitor LVM Disk space left on NewRelic
Home-page: https://github.com/WebGeoServices/newrelic_lvm_plugin
Author: WebGeoServices
Author-email: operation@webgeoservices.com
License: MIT
Download-URL: https://github.com/WebGeoServices/newrelic_lvm_plugin/tarball/0.1
Keywords: newrelic,LVM,Thinpool
Platform: UNKNOWN
